updater/__init__.py
updater/llm_prompts/archived/check_and_merge_opns_sys.txt
updater/llm_prompts/archived/check_and_merge_opns_user.txt
updater/llm_prompts/archived/extract_opn_breakdown_sys.txt
updater/llm_prompts/archived/extract_opn_breakdown_sys_old.txt
updater/llm_prompts/archived/extract_opn_breakdown_user.txt
updater/llm_prompts/archived/gen_use_cases_subreddit_sys.txt
updater/llm_prompts/archived/gen_use_cases_sys.txt
updater/llm_prompts/archived/gen_use_cases_user.txt
updater/llm_prompts/archived/group_variations_sys.txt
updater/llm_prompts/archived/has_opn_sys.txt
updater/llm_prompts/get_options_spec_from_amzn_info_sys.txt
updater/llm_prompts/get_options_spec_from_amzn_info_user.txt
updater/llm_prompts/get_pd_brand.txt
updater/llm_prompts/get_range_spec_from_amzn_info_sys.txt
updater/llm_prompts/get_range_spec_from_amzn_info_user.txt
updater/llm_prompts/group_variations_sys.txt
updater/llm_prompts/has_opn_sys.txt
updater/llm_prompts/identify_opn_sys.txt
updater/llm_prompts/is_amzn_item_match_pd_info_sys.txt
updater/llm_prompts/is_google_amzn_item_match_pd_info_sys.txt
updater/llm_prompts/is_opn_sys.txt
updater/llm_prompts/is_owner_sys.txt
updater/llm_prompts/refine_pd_category_user.txt
updater/main.py
updater/pipeline/__init__.py
updater/pipeline/archived/extract_opn_breakdown.py
updater/pipeline/archived/gen_use_cases.py
updater/pipeline/archived/gen_use_cases_from_subreddit.py
updater/pipeline/check_n_update_specs.py
updater/pipeline/furnish_pd_info.py
updater/pipeline/furnish_sources.py
updater/pipeline/gen_search_terms.py
updater/pipeline/get_amzn_pd_info.py
updater/pipeline/get_pd_brand.py
updater/pipeline/has_opns_from_scan.py
updater/pipeline/identify_opns.py
updater/pipeline/perform_checks_on_opns.py
updater/pipeline/prep_subm_for_llm.py
updater/pipeline/process_parent_asin.py
updater/pipeline/refine_new_pd_category.py
updater/pipeline/search.py
updater/reddit_blacklist.py
updater/utils/__init__.py
updater/utils/ai_handler.py
reddit_recs_updater-0.1.53.dist-info/METADATA
reddit_recs_updater-0.1.53.dist-info/WHEEL
reddit_recs_updater-0.1.53.dist-info/RECORD
