Metadata-Version: 2.1
Name: reddit-recs-updater
Version: 0.1.53
Summary: Modules to get recs and update db
Author: Joo
Author-email: joo@redditrecs.com
Requires-Python: >=3.12,<4.0
Classifier: Programming Language :: Python :: 3
Requires-Dist: aiocache (>=0.12.3,<0.13.0)
Requires-Dist: aiohttp (>=3.10.10,<4.0.0)
Requires-Dist: asyncio
Requires-Dist: asyncpraw (==7.7.1)
Requires-Dist: asyncprawcore (==2.4.0)
Requires-Dist: beautifulsoup4 (==4.12.3)
Requires-Dist: groq
Requires-Dist: instructor (>=1.6.1,<2.0.0)
Requires-Dist: openai
Requires-Dist: praw (==7.7.1)
Requires-Dist: prawcore (==2.4.0)
Requires-Dist: pydantic (==2.8.2)
Requires-Dist: pytest (>=8.3.3,<9.0.0)
Requires-Dist: pytest-asyncio (>=0.24.0,<0.25.0)
Requires-Dist: python-dotenv (==1.0.1)
Requires-Dist: replit (>=4.0.0,<5.0.0)
Requires-Dist: requests (==2.32.3)
Requires-Dist: six (==1.16.0)
Requires-Dist: sse-starlette (>=2.1.3,<3.0.0)
Requires-Dist: supabase (>=2.7.2,<3.0.0)
